<?xml version="1.0" encoding="UTF-8"?>
<Entities
 majorVersion="9"
 minorVersion="3"
 universal="password">
    <ThingShapes>
        <ThingShape
         aspect.isEditableExtensionObject="false"
         aspect.isExtension="true"
         className=""
         description="Thing Shape Interface for containing core component services. Every Component will need to implement this interface. This will contain services that will support Solution Configuration Pages etc."
         documentationContent=""
         homeMashup=""
         name="PTC.Base.ComponentInterface_TS"
         projectName="PTC.Base"
         tags="">
            <PropertyDefinitions>
                <PropertyDefinition
                 aspect.cacheTime="0.0"
                 aspect.dataChangeType="VALUE"
                 aspect.isPersistent="true"
                 baseType="STRING"
                 category=""
                 description=""
                 isLocalOnly="false"
                 name="componentDefaultOrg"
                 ordinal="11"></PropertyDefinition>
                <PropertyDefinition
                 aspect.cacheTime="0.0"
                 aspect.dataChangeType="VALUE"
                 aspect.isPersistent="true"
                 baseType="STRING"
                 category=""
                 description=""
                 isLocalOnly="false"
                 name="componentDefaultUserGroup"
                 ordinal="12"></PropertyDefinition>
                <PropertyDefinition
                 aspect.cacheTime="0.0"
                 aspect.dataChangeType="VALUE"
                 aspect.defaultValue="Not Configured"
                 aspect.isPersistent="true"
                 baseType="STRING"
                 category=""
                 description="The deployment state of the building block. Can be either 'Not Configured', 'Configured', or 'Error' state."
                 isLocalOnly="false"
                 name="componentDeploymentState"
                 ordinal="11"></PropertyDefinition>
                <PropertyDefinition
                 aspect.cacheTime="0.0"
                 aspect.dataChangeType="VALUE"
                 aspect.isPersistent="true"
                 baseType="STRING"
                 category=""
                 description=""
                 isLocalOnly="false"
                 name="componentDescription"
                 ordinal="13"></PropertyDefinition>
                <PropertyDefinition
                 aspect.cacheTime="0.0"
                 aspect.dataChangeType="VALUE"
                 aspect.isPersistent="true"
                 baseType="STRING"
                 category=""
                 description=""
                 isLocalOnly="false"
                 name="componentMainMashup"
                 ordinal="14"></PropertyDefinition>
                <PropertyDefinition
                 aspect.cacheTime="0.0"
                 aspect.dataChangeType="VALUE"
                 aspect.isPersistent="true"
                 baseType="STRING"
                 category=""
                 description=""
                 isLocalOnly="false"
                 name="componentName"
                 ordinal="15"></PropertyDefinition>
                <PropertyDefinition
                 aspect.cacheTime="0.0"
                 aspect.dataChangeType="VALUE"
                 aspect.isPersistent="true"
                 baseType="IMAGELINK"
                 category=""
                 description=""
                 isLocalOnly="false"
                 name="componentThumbnail"
                 ordinal="16"></PropertyDefinition>
                <PropertyDefinition
                 aspect.cacheTime="0.0"
                 aspect.dataChangeType="VALUE"
                 aspect.isPersistent="true"
                 baseType="STRING"
                 category=""
                 description=""
                 isLocalOnly="false"
                 name="componentType"
                 ordinal="17"></PropertyDefinition>
                <PropertyDefinition
                 aspect.cacheTime="0.0"
                 aspect.dataChangeType="VALUE"
                 aspect.isPersistent="true"
                 baseType="STRING"
                 category=""
                 description=""
                 isLocalOnly="false"
                 name="componentVersion"
                 ordinal="18"></PropertyDefinition>
                <PropertyDefinition
                 aspect.cacheTime="0.0"
                 aspect.dataChangeType="VALUE"
                 aspect.dataShape="PTC.Base.DependentComponents"
                 aspect.isPersistent="true"
                 baseType="INFOTABLE"
                 category=""
                 description="List of Components that are needed for this component to function"
                 isLocalOnly="false"
                 name="dependentComponents"
                 ordinal="19"></PropertyDefinition>
                <PropertyDefinition
                 aspect.cacheTime="0.0"
                 aspect.dataChangeType="VALUE"
                 aspect.dataShape="PTC.Base.ComponentConfigStatus"
                 aspect.isPersistent="true"
                 baseType="INFOTABLE"
                 category=""
                 description="Status of Deployment."
                 isLocalOnly="false"
                 name="deployComponentStatus"
                 ordinal="14"></PropertyDefinition>
                <PropertyDefinition
                 aspect.cacheTime="0.0"
                 aspect.dataChangeType="VALUE"
                 aspect.dataShape="PTC.Base.ComponentConfigStatus"
                 aspect.isPersistent="true"
                 baseType="INFOTABLE"
                 category=""
                 description="Status of Migrate."
                 isLocalOnly="false"
                 name="migrateComponentStatus"
                 ordinal="15"></PropertyDefinition>
                <PropertyDefinition
                 aspect.cacheTime="0.0"
                 aspect.dataChangeType="VALUE"
                 aspect.dataShape="PTC.Base.ComponentConfigStatus"
                 aspect.isPersistent="true"
                 baseType="INFOTABLE"
                 category=""
                 description="Status of Upgrade."
                 isLocalOnly="false"
                 name="upgradeComponentStatus"
                 ordinal="16"></PropertyDefinition>
            </PropertyDefinitions>
            <ServiceDefinitions>
                <ServiceDefinition
                 aspect.isAsync="false"
                 category=""
                 description="Override-able service to handle any post install deployments/configurations."
                 isAllowOverride="true"
                 isLocalOnly="false"
                 isOpen="false"
                 isPrivate="false"
                 name="DeployComponent">
                    <ResultType
                     baseType="BOOLEAN"
                     description="returns true or false depending on if deployment was successful. "
                     name="result"
                     ordinal="0"></ResultType>
                    <ParameterDefinitions>
                        <FieldDefinition
                         baseType="JSON"
                         description="Optional JSON Deployment config"
                         name="deploymentConfig"
                         ordinal="1"></FieldDefinition>
                    </ParameterDefinitions>
                </ServiceDefinition>
                <ServiceDefinition
                 aspect.isAsync="false"
                 category=""
                 description="Returns the Component Deploy Configuration Parameters property"
                 isAllowOverride="true"
                 isLocalOnly="false"
                 isOpen="false"
                 isPrivate="false"
                 name="GetComponentDeployConfigurationParameters">
                    <ResultType
                     baseType="JSON"
                     description=""
                     name="result"
                     ordinal="0"></ResultType>
                    <ParameterDefinitions></ParameterDefinitions>
                </ServiceDefinition>
                <ServiceDefinition
                 aspect.isAsync="false"
                 category=""
                 description="Returns the Component Description property"
                 isAllowOverride="true"
                 isLocalOnly="false"
                 isOpen="false"
                 isPrivate="false"
                 name="GetComponentDescription">
                    <ResultType
                     baseType="STRING"
                     description=""
                     name="result"
                     ordinal="0"></ResultType>
                    <ParameterDefinitions></ParameterDefinitions>
                </ServiceDefinition>
                <ServiceDefinition
                 aspect.isAsync="false"
                 category=""
                 description="This service returns the extension version and build number for the given component."
                 isAllowOverride="true"
                 isLocalOnly="false"
                 isOpen="false"
                 isPrivate="false"
                 name="GetComponentExtensionVersion">
                    <ResultType
                     baseType="STRING"
                     description=""
                     name="result"
                     ordinal="0"></ResultType>
                    <ParameterDefinitions></ParameterDefinitions>
                </ServiceDefinition>
                <ServiceDefinition
                 aspect.isAsync="false"
                 category=""
                 description="Returns the Component Main Mashup property."
                 isAllowOverride="true"
                 isLocalOnly="false"
                 isOpen="false"
                 isPrivate="false"
                 name="GetComponentMainMashup">
                    <ResultType
                     baseType="MASHUPNAME"
                     description=""
                     name="result"
                     ordinal="0"></ResultType>
                    <ParameterDefinitions></ParameterDefinitions>
                </ServiceDefinition>
                <ServiceDefinition
                 aspect.isAsync="false"
                 category=""
                 description="Returns the Migrate Component Configuration Parameters property"
                 isAllowOverride="true"
                 isLocalOnly="false"
                 isOpen="false"
                 isPrivate="false"
                 name="GetComponentMigrateConfigurationParameters">
                    <ResultType
                     baseType="JSON"
                     description=""
                     name="result"
                     ordinal="0"></ResultType>
                    <ParameterDefinitions></ParameterDefinitions>
                </ServiceDefinition>
                <ServiceDefinition
                 aspect.isAsync="false"
                 category=""
                 description="Return the Component Name property"
                 isAllowOverride="true"
                 isLocalOnly="false"
                 isOpen="false"
                 isPrivate="false"
                 name="GetComponentName">
                    <ResultType
                     baseType="STRING"
                     description=""
                     name="result"
                     ordinal="0"></ResultType>
                    <ParameterDefinitions></ParameterDefinitions>
                </ServiceDefinition>
                <ServiceDefinition
                 aspect.isAsync="false"
                 category=""
                 description="Returns the Component Provided Elements property."
                 isAllowOverride="true"
                 isLocalOnly="false"
                 isOpen="false"
                 isPrivate="false"
                 name="GetComponentProvidedElements">
                    <ResultType
                     aspect.dataShape="EntityReference"
                     baseType="INFOTABLE"
                     description=""
                     name="result"
                     ordinal="0"></ResultType>
                    <ParameterDefinitions></ParameterDefinitions>
                </ServiceDefinition>
                <ServiceDefinition
                 aspect.isAsync="false"
                 category=""
                 description="Returns the Component Required Elements property"
                 isAllowOverride="true"
                 isLocalOnly="false"
                 isOpen="false"
                 isPrivate="false"
                 name="GetComponentRequiredElements">
                    <ResultType
                     aspect.dataShape="EntityReference"
                     baseType="INFOTABLE"
                     description=""
                     name="result"
                     ordinal="0"></ResultType>
                    <ParameterDefinitions></ParameterDefinitions>
                </ServiceDefinition>
                <ServiceDefinition
                 aspect.isAsync="false"
                 category=""
                 description="Returns the Component Thumbnail "
                 isAllowOverride="true"
                 isLocalOnly="false"
                 isOpen="false"
                 isPrivate="false"
                 name="GetComponentThumbnail">
                    <ResultType
                     baseType="IMAGELINK"
                     description=""
                     name="result"
                     ordinal="0"></ResultType>
                    <ParameterDefinitions></ParameterDefinitions>
                </ServiceDefinition>
                <ServiceDefinition
                 aspect.isAsync="false"
                 category=""
                 description="Returns the Component Type property"
                 isAllowOverride="true"
                 isLocalOnly="false"
                 isOpen="false"
                 isPrivate="false"
                 name="GetComponentType">
                    <ResultType
                     baseType="STRING"
                     description=""
                     name="result"
                     ordinal="0"></ResultType>
                    <ParameterDefinitions></ParameterDefinitions>
                </ServiceDefinition>
                <ServiceDefinition
                 aspect.isAsync="false"
                 category=""
                 description="Returns the Upgrade Component Configuration Parameters property"
                 isAllowOverride="true"
                 isLocalOnly="false"
                 isOpen="false"
                 isPrivate="false"
                 name="GetComponentUpgradeConfigurationParameters">
                    <ResultType
                     baseType="JSON"
                     description=""
                     name="result"
                     ordinal="0"></ResultType>
                    <ParameterDefinitions></ParameterDefinitions>
                </ServiceDefinition>
                <ServiceDefinition
                 aspect.isAsync="false"
                 category=""
                 description="Returns component version property"
                 isAllowOverride="true"
                 isLocalOnly="false"
                 isOpen="false"
                 isPrivate="false"
                 name="GetComponentVersion">
                    <ResultType
                     baseType="STRING"
                     description=""
                     name="result"
                     ordinal="0"></ResultType>
                    <ParameterDefinitions></ParameterDefinitions>
                </ServiceDefinition>
                <ServiceDefinition
                 aspect.isAsync="false"
                 category=""
                 description="Returns the configured default component manager thing."
                 isAllowOverride="true"
                 isLocalOnly="false"
                 isOpen="false"
                 isPrivate="false"
                 name="GetConfiguredComponentManager">
                    <ResultType
                     baseType="THINGNAME"
                     description=""
                     name="result"
                     ordinal="0"></ResultType>
                    <ParameterDefinitions></ParameterDefinitions>
                </ServiceDefinition>
                <ServiceDefinition
                 aspect.isAsync="false"
                 category=""
                 description="Migrate component to the latest."
                 isAllowOverride="true"
                 isLocalOnly="false"
                 isOpen="false"
                 isPrivate="false"
                 name="MigrateComponent">
                    <ResultType
                     aspect.dataShape="PTC.Base.ComponentConfigStatus"
                     baseType="INFOTABLE"
                     description=""
                     name="result"
                     ordinal="0"></ResultType>
                    <ParameterDefinitions>
                        <FieldDefinition
                         aspect.isRequired="false"
                         baseType="JSON"
                         description="Optional JSON config."
                         name="config"
                         ordinal="1"></FieldDefinition>
                    </ParameterDefinitions>
                </ServiceDefinition>
                <ServiceDefinition
                 aspect.isAsync="false"
                 category=""
                 description="Runs validations and actions necessary before data related to a component (building block) is migrated."
                 isAllowOverride="true"
                 isLocalOnly="false"
                 isOpen="false"
                 isPrivate="false"
                 name="PreMigrateComponent">
                    <ResultType
                     aspect.dataShape="PTC.Base.ComponentConfigStatus"
                     baseType="INFOTABLE"
                     description=""
                     name="result"
                     ordinal="0"></ResultType>
                    <ParameterDefinitions>
                        <FieldDefinition
                         baseType="JSON"
                         description="Optional JSON config."
                         name="config"
                         ordinal="1"></FieldDefinition>
                    </ParameterDefinitions>
                </ServiceDefinition>
                <ServiceDefinition
                 aspect.isAsync="false"
                 category=""
                 description="Runs validations and actions necessary before a component (building block) is upgraded."
                 isAllowOverride="true"
                 isLocalOnly="false"
                 isOpen="false"
                 isPrivate="false"
                 name="PreUpgradeComponent">
                    <ResultType
                     aspect.dataShape="PTC.Base.ComponentConfigStatus"
                     baseType="INFOTABLE"
                     description=""
                     name="result"
                     ordinal="0"></ResultType>
                    <ParameterDefinitions>
                        <FieldDefinition
                         baseType="JSON"
                         description="Optional JSON config."
                         name="config"
                         ordinal="1"></FieldDefinition>
                    </ParameterDefinitions>
                </ServiceDefinition>
                <ServiceDefinition
                 aspect.isAsync="false"
                 category=""
                 description="Upgrade component to the latest."
                 isAllowOverride="true"
                 isLocalOnly="false"
                 isOpen="false"
                 isPrivate="false"
                 name="UpgradeComponent">
                    <ResultType
                     aspect.dataShape="PTC.Base.ComponentConfigStatus"
                     baseType="INFOTABLE"
                     description=""
                     name="result"
                     ordinal="0"></ResultType>
                    <ParameterDefinitions>
                        <FieldDefinition
                         baseType="JSON"
                         description="Optional JSON config."
                         name="config"
                         ordinal="1"></FieldDefinition>
                    </ParameterDefinitions>
                </ServiceDefinition>
                <ServiceDefinition
                 aspect.isAsync="false"
                 category=""
                 description="Validates the component deploy config parameters against the passed in JSON payload."
                 isAllowOverride="true"
                 isLocalOnly="false"
                 isOpen="false"
                 isPrivate="false"
                 name="ValidateComponentDeployConfigParams">
                    <ResultType
                     baseType="BOOLEAN"
                     description=""
                     name="result"
                     ordinal="0"></ResultType>
                    <ParameterDefinitions>
                        <FieldDefinition
                         aspect.isRequired="true"
                         baseType="JSON"
                         description="passed in JSON params to compare against the components params."
                         name="jsonParams"
                         ordinal="1"></FieldDefinition>
                    </ParameterDefinitions>
                </ServiceDefinition>
                <ServiceDefinition
                 aspect.isAsync="false"
                 category=""
                 description="Validates the component migrate config parameters against the passed in JSON payload."
                 isAllowOverride="true"
                 isLocalOnly="false"
                 isOpen="false"
                 isPrivate="false"
                 name="ValidateComponentMigrateConfigParams">
                    <ResultType
                     baseType="BOOLEAN"
                     description=""
                     name="result"
                     ordinal="0"></ResultType>
                    <ParameterDefinitions>
                        <FieldDefinition
                         aspect.isRequired="true"
                         baseType="JSON"
                         description="passed in JSON params to compare against the components params."
                         name="jsonParams"
                         ordinal="1"></FieldDefinition>
                    </ParameterDefinitions>
                </ServiceDefinition>
                <ServiceDefinition
                 aspect.isAsync="false"
                 category=""
                 description="Validates the component upgrade config parameters against the passed in JSON payload."
                 isAllowOverride="true"
                 isLocalOnly="false"
                 isOpen="false"
                 isPrivate="false"
                 name="ValidateComponentUpgradeConfigParams">
                    <ResultType
                     baseType="BOOLEAN"
                     description=""
                     name="result"
                     ordinal="0"></ResultType>
                    <ParameterDefinitions>
                        <FieldDefinition
                         aspect.isRequired="true"
                         baseType="JSON"
                         description="passed in JSON params to compare against the components params."
                         name="jsonParams"
                         ordinal="1"></FieldDefinition>
                    </ParameterDefinitions>
                </ServiceDefinition>
            </ServiceDefinitions>
            <EventDefinitions></EventDefinitions>
            <ServiceMappings></ServiceMappings>
            <ServiceImplementations>
                <ServiceImplementation
                 description=""
                 handlerName="Script"
                 name="DeployComponent">
                    <ConfigurationTables>
                        <ConfigurationTable
                         dataShapeName=""
                         description=""
                         isMultiRow="false"
                         name="Script"
                         ordinal="0">
                            <DataShape>
                                <FieldDefinitions>
                                    <FieldDefinition
                                     baseType="STRING"
                                     description="code"
                                     name="code"
                                     ordinal="0"></FieldDefinition>
                                </FieldDefinitions>
                            </DataShape>
                            <Rows>
                                <Row>
                                    <code>
                                    <![CDATA[
                                    // Return true as a default
                                    var result = true;
                                    ]]>
                                    </code>
                                </Row>
                            </Rows>
                        </ConfigurationTable>
                    </ConfigurationTables>
                </ServiceImplementation>
                <ServiceImplementation
                 description=""
                 handlerName="Script"
                 name="GetComponentDeployConfigurationParameters">
                    <ConfigurationTables>
                        <ConfigurationTable
                         dataShapeName=""
                         description=""
                         isMultiRow="false"
                         name="Script"
                         ordinal="0">
                            <DataShape>
                                <FieldDefinitions>
                                    <FieldDefinition
                                     baseType="STRING"
                                     description="code"
                                     name="code"
                                     ordinal="0"></FieldDefinition>
                                </FieldDefinitions>
                            </DataShape>
                            <Rows>
                                <Row>
                                    <code>
                                    <![CDATA[
                                    var result = {};
                                    ]]>
                                    </code>
                                </Row>
                            </Rows>
                        </ConfigurationTable>
                    </ConfigurationTables>
                </ServiceImplementation>
                <ServiceImplementation
                 description=""
                 handlerName="Script"
                 name="GetComponentDescription">
                    <ConfigurationTables>
                        <ConfigurationTable
                         dataShapeName=""
                         description=""
                         isMultiRow="false"
                         name="Script"
                         ordinal="0">
                            <DataShape>
                                <FieldDefinitions>
                                    <FieldDefinition
                                     baseType="STRING"
                                     description="code"
                                     name="code"
                                     ordinal="0"></FieldDefinition>
                                </FieldDefinitions>
                            </DataShape>
                            <Rows>
                                <Row>
                                    <code></code>
                                </Row>
                            </Rows>
                        </ConfigurationTable>
                    </ConfigurationTables>
                </ServiceImplementation>
                <ServiceImplementation
                 description=""
                 handlerName="Script"
                 name="GetComponentExtensionVersion">
                    <ConfigurationTables>
                        <ConfigurationTable
                         dataShapeName=""
                         description=""
                         isMultiRow="false"
                         name="Script"
                         ordinal="0">
                            <DataShape>
                                <FieldDefinitions>
                                    <FieldDefinition
                                     baseType="STRING"
                                     description="code"
                                     name="code"
                                     ordinal="0"></FieldDefinition>
                                </FieldDefinitions>
                            </DataShape>
                            <Rows>
                                <Row>
                                    <code></code>
                                </Row>
                            </Rows>
                        </ConfigurationTable>
                    </ConfigurationTables>
                </ServiceImplementation>
                <ServiceImplementation
                 description=""
                 handlerName="Script"
                 name="GetComponentMainMashup">
                    <ConfigurationTables>
                        <ConfigurationTable
                         dataShapeName=""
                         description=""
                         isMultiRow="false"
                         name="Script"
                         ordinal="0">
                            <DataShape>
                                <FieldDefinitions>
                                    <FieldDefinition
                                     baseType="STRING"
                                     description="code"
                                     name="code"
                                     ordinal="0"></FieldDefinition>
                                </FieldDefinitions>
                            </DataShape>
                            <Rows>
                                <Row>
                                    <code>
                                    <![CDATA[
                                    try {
                                    	var result = me.componentMainMashup;
                                    } catch (err) {
                                        logger.error("{} - {}:{} - {}", me.name, err.fileName, err.lineNumber, err);
                                    	throw ("An error has occurred. Please check the script logs for more details.");
                                    }
                                    ]]>
                                    </code>
                                </Row>
                            </Rows>
                        </ConfigurationTable>
                    </ConfigurationTables>
                </ServiceImplementation>
                <ServiceImplementation
                 description=""
                 handlerName="Script"
                 name="GetComponentMigrateConfigurationParameters">
                    <ConfigurationTables>
                        <ConfigurationTable
                         dataShapeName=""
                         description=""
                         isMultiRow="false"
                         name="Script"
                         ordinal="0">
                            <DataShape>
                                <FieldDefinitions>
                                    <FieldDefinition
                                     baseType="STRING"
                                     description="code"
                                     name="code"
                                     ordinal="0"></FieldDefinition>
                                </FieldDefinitions>
                            </DataShape>
                            <Rows>
                                <Row>
                                    <code>
                                    <![CDATA[
                                    var result = {};
                                    ]]>
                                    </code>
                                </Row>
                            </Rows>
                        </ConfigurationTable>
                    </ConfigurationTables>
                </ServiceImplementation>
                <ServiceImplementation
                 description=""
                 handlerName="Script"
                 name="GetComponentName">
                    <ConfigurationTables>
                        <ConfigurationTable
                         dataShapeName=""
                         description=""
                         isMultiRow="false"
                         name="Script"
                         ordinal="0">
                            <DataShape>
                                <FieldDefinitions>
                                    <FieldDefinition
                                     baseType="STRING"
                                     description="code"
                                     name="code"
                                     ordinal="0"></FieldDefinition>
                                </FieldDefinitions>
                            </DataShape>
                            <Rows>
                                <Row>
                                    <code></code>
                                </Row>
                            </Rows>
                        </ConfigurationTable>
                    </ConfigurationTables>
                </ServiceImplementation>
                <ServiceImplementation
                 description=""
                 handlerName="Script"
                 name="GetComponentProvidedElements">
                    <ConfigurationTables>
                        <ConfigurationTable
                         dataShapeName=""
                         description=""
                         isMultiRow="false"
                         name="Script"
                         ordinal="0">
                            <DataShape>
                                <FieldDefinitions>
                                    <FieldDefinition
                                     baseType="STRING"
                                     description="code"
                                     name="code"
                                     ordinal="0"></FieldDefinition>
                                </FieldDefinitions>
                            </DataShape>
                            <Rows>
                                <Row>
                                    <code></code>
                                </Row>
                            </Rows>
                        </ConfigurationTable>
                    </ConfigurationTables>
                </ServiceImplementation>
                <ServiceImplementation
                 description=""
                 handlerName="Script"
                 name="GetComponentRequiredElements">
                    <ConfigurationTables>
                        <ConfigurationTable
                         dataShapeName=""
                         description=""
                         isMultiRow="false"
                         name="Script"
                         ordinal="0">
                            <DataShape>
                                <FieldDefinitions>
                                    <FieldDefinition
                                     baseType="STRING"
                                     description="code"
                                     name="code"
                                     ordinal="0"></FieldDefinition>
                                </FieldDefinitions>
                            </DataShape>
                            <Rows>
                                <Row>
                                    <code></code>
                                </Row>
                            </Rows>
                        </ConfigurationTable>
                    </ConfigurationTables>
                </ServiceImplementation>
                <ServiceImplementation
                 description=""
                 handlerName="Script"
                 name="GetComponentThumbnail">
                    <ConfigurationTables>
                        <ConfigurationTable
                         dataShapeName=""
                         description=""
                         isMultiRow="false"
                         name="Script"
                         ordinal="0">
                            <DataShape>
                                <FieldDefinitions>
                                    <FieldDefinition
                                     baseType="STRING"
                                     description="code"
                                     name="code"
                                     ordinal="0"></FieldDefinition>
                                </FieldDefinitions>
                            </DataShape>
                            <Rows>
                                <Row>
                                    <code></code>
                                </Row>
                            </Rows>
                        </ConfigurationTable>
                    </ConfigurationTables>
                </ServiceImplementation>
                <ServiceImplementation
                 description=""
                 handlerName="Script"
                 name="GetComponentType">
                    <ConfigurationTables>
                        <ConfigurationTable
                         dataShapeName=""
                         description=""
                         isMultiRow="false"
                         name="Script"
                         ordinal="0">
                            <DataShape>
                                <FieldDefinitions>
                                    <FieldDefinition
                                     baseType="STRING"
                                     description="code"
                                     name="code"
                                     ordinal="0"></FieldDefinition>
                                </FieldDefinitions>
                            </DataShape>
                            <Rows>
                                <Row>
                                    <code></code>
                                </Row>
                            </Rows>
                        </ConfigurationTable>
                    </ConfigurationTables>
                </ServiceImplementation>
                <ServiceImplementation
                 description=""
                 handlerName="Script"
                 name="GetComponentUpgradeConfigurationParameters">
                    <ConfigurationTables>
                        <ConfigurationTable
                         dataShapeName=""
                         description=""
                         isMultiRow="false"
                         name="Script"
                         ordinal="0">
                            <DataShape>
                                <FieldDefinitions>
                                    <FieldDefinition
                                     baseType="STRING"
                                     description="code"
                                     name="code"
                                     ordinal="0"></FieldDefinition>
                                </FieldDefinitions>
                            </DataShape>
                            <Rows>
                                <Row>
                                    <code>
                                    <![CDATA[
                                    var result = {};
                                    ]]>
                                    </code>
                                </Row>
                            </Rows>
                        </ConfigurationTable>
                    </ConfigurationTables>
                </ServiceImplementation>
                <ServiceImplementation
                 description=""
                 handlerName="Script"
                 name="GetComponentVersion">
                    <ConfigurationTables>
                        <ConfigurationTable
                         dataShapeName=""
                         description=""
                         isMultiRow="false"
                         name="Script"
                         ordinal="0">
                            <DataShape>
                                <FieldDefinitions>
                                    <FieldDefinition
                                     baseType="STRING"
                                     description="code"
                                     name="code"
                                     ordinal="0"></FieldDefinition>
                                </FieldDefinitions>
                            </DataShape>
                            <Rows>
                                <Row>
                                    <code></code>
                                </Row>
                            </Rows>
                        </ConfigurationTable>
                    </ConfigurationTables>
                </ServiceImplementation>
                <ServiceImplementation
                 description=""
                 handlerName="Script"
                 name="GetConfiguredComponentManager">
                    <ConfigurationTables>
                        <ConfigurationTable
                         dataShapeName=""
                         description=""
                         isMultiRow="false"
                         name="Script"
                         ordinal="0">
                            <DataShape>
                                <FieldDefinitions>
                                    <FieldDefinition
                                     baseType="STRING"
                                     description="code"
                                     name="code"
                                     ordinal="0"></FieldDefinition>
                                </FieldDefinitions>
                            </DataShape>
                            <Rows>
                                <Row>
                                    <code>
                                    <![CDATA[
                                    var result;
                                    
                                    try {
                                    	let configTable = me.GetConfigurationTable({
                                    		tableName: "ComponentManager" /* STRING */
                                    	});
                                    
                                    	if (configTable && configTable.length > 0) {
                                    		configTable.rows.toArray().forEach(row => {
                                    			if (row.id == "ComponentManager") {
                                    				result = row.managerThingName;
                                    			}
                                    		});
                                    	}
                                    
                                    	let projectName = me.GetProjectName();
                                    	if (!result && projectName != "PTC.Base") {
                                    		let abstractProjectName;
                                    		try {
                                    			abstractProjectName = me.GetAbstractComponentBuildingBlockName();
                                    		} catch (err) {
                                    			logger.warn("{} - {}:{} - {}. Could not retrieve abstract project name, defaulting current project Name [{}]", me.name, err.fileName, err.lineNumber, err, projectName);
                                    			abstractProjectName = projectName;
                                    		}
                                    		let identifier = abstractProjectName + ".Manager";
                                    		let baseManager = Things["PTC.Base.EntryPoint"].GetConfiguredComponentManager();
                                    		result = Things[baseManager].GetGlobalDefaultManagerForIdentifier({
                                    			uid: identifier
                                    		});
                                    	}
                                    } catch (err) {
                                    	logger.error("{} - {}:{} - {}", me.name, err.fileName, err.lineNumber, err);
                                    	throw ("An error has occurred. Please check the script logs for more details.");
                                    }
                                    ]]>
                                    </code>
                                </Row>
                            </Rows>
                        </ConfigurationTable>
                    </ConfigurationTables>
                </ServiceImplementation>
                <ServiceImplementation
                 description=""
                 handlerName="Script"
                 name="MigrateComponent">
                    <ConfigurationTables>
                        <ConfigurationTable
                         dataShapeName=""
                         description=""
                         isMultiRow="false"
                         name="Script"
                         ordinal="0">
                            <DataShape>
                                <FieldDefinitions>
                                    <FieldDefinition
                                     baseType="STRING"
                                     description="code"
                                     name="code"
                                     ordinal="0"></FieldDefinition>
                                </FieldDefinitions>
                            </DataShape>
                            <Rows>
                                <Row>
                                    <code>
                                    <![CDATA[
                                    result = me.migrateComponentStatus;
                                    ]]>
                                    </code>
                                </Row>
                            </Rows>
                        </ConfigurationTable>
                    </ConfigurationTables>
                </ServiceImplementation>
                <ServiceImplementation
                 description=""
                 handlerName="Script"
                 name="PreMigrateComponent">
                    <ConfigurationTables>
                        <ConfigurationTable
                         dataShapeName=""
                         description=""
                         isMultiRow="false"
                         name="Script"
                         ordinal="0">
                            <DataShape>
                                <FieldDefinitions>
                                    <FieldDefinition
                                     baseType="STRING"
                                     description="code"
                                     name="code"
                                     ordinal="0"></FieldDefinition>
                                </FieldDefinitions>
                            </DataShape>
                            <Rows>
                                <Row>
                                    <code>
                                    <![CDATA[
                                    var result = DataShapes["PTC.Base.ComponentConfigStatus"].CreateValues();
                                    let validationStatus = "Success";
                                    let validationMessage = "Pre migrate validation is successful";
                                    //perform validations here, if validation fails, override validationStatus to Error and provide proper validationMessage
                                    let row = {
                                    	name: me.GetProjectName(),
                                    	type: "PreMigrate",
                                    	status: validationStatus,
                                    	additionalInfo: {
                                    		message: validationMessage
                                    	}
                                    };
                                    result.AddRow(row);
                                    ]]>
                                    </code>
                                </Row>
                            </Rows>
                        </ConfigurationTable>
                    </ConfigurationTables>
                </ServiceImplementation>
                <ServiceImplementation
                 description=""
                 handlerName="Script"
                 name="PreUpgradeComponent">
                    <ConfigurationTables>
                        <ConfigurationTable
                         dataShapeName=""
                         description=""
                         isMultiRow="false"
                         name="Script"
                         ordinal="0">
                            <DataShape>
                                <FieldDefinitions>
                                    <FieldDefinition
                                     baseType="STRING"
                                     description="code"
                                     name="code"
                                     ordinal="0"></FieldDefinition>
                                </FieldDefinitions>
                            </DataShape>
                            <Rows>
                                <Row>
                                    <code>
                                    <![CDATA[
                                    var result = DataShapes["PTC.Base.ComponentConfigStatus"].CreateValues();
                                    let validationStatus = "Success";
                                    let validationMessage = "Pre upgrade validation is successful";
                                    //perform validations, if validation fails, override validationStatus to Error and provide proper validationMessage
                                    let row = {
                                    	name: me.GetProjectName(),
                                    	type: "PreUpgrade",
                                    	status: validationStatus,
                                    	additionalInfo: {
                                    		message: validationMessage
                                    	}
                                    };
                                    result.AddRow(row);
                                    ]]>
                                    </code>
                                </Row>
                            </Rows>
                        </ConfigurationTable>
                    </ConfigurationTables>
                </ServiceImplementation>
                <ServiceImplementation
                 description=""
                 handlerName="Script"
                 name="UpgradeComponent">
                    <ConfigurationTables>
                        <ConfigurationTable
                         dataShapeName=""
                         description=""
                         isMultiRow="false"
                         name="Script"
                         ordinal="0">
                            <DataShape>
                                <FieldDefinitions>
                                    <FieldDefinition
                                     baseType="STRING"
                                     description="code"
                                     name="code"
                                     ordinal="0"></FieldDefinition>
                                </FieldDefinitions>
                            </DataShape>
                            <Rows>
                                <Row>
                                    <code>
                                    <![CDATA[
                                    result = me.upgradeComponentStatus;
                                    ]]>
                                    </code>
                                </Row>
                            </Rows>
                        </ConfigurationTable>
                    </ConfigurationTables>
                </ServiceImplementation>
                <ServiceImplementation
                 description=""
                 handlerName="Script"
                 name="ValidateComponentDeployConfigParams">
                    <ConfigurationTables>
                        <ConfigurationTable
                         dataShapeName=""
                         description=""
                         isMultiRow="false"
                         name="Script"
                         ordinal="0">
                            <DataShape>
                                <FieldDefinitions>
                                    <FieldDefinition
                                     baseType="STRING"
                                     description="code"
                                     name="code"
                                     ordinal="0"></FieldDefinition>
                                </FieldDefinitions>
                            </DataShape>
                            <Rows>
                                <Row>
                                    <code>
                                    <![CDATA[
                                    var result = true;
                                    try {
                                    	let componentParams = me.GetComponentDeployConfigurationParameters();
                                    	for (let key in componentParams) {
                                    		if (!jsonParams[key] && !componentParams[key].optional) {
                                    			result = false;
                                    		}
                                    	}
                                    } catch (err) {
                                    	logger.error(me.name + " - " + err.fileName + ":" + err.lineNumber + " - " + err);
                                    	throw err;
                                    }
                                    ]]>
                                    </code>
                                </Row>
                            </Rows>
                        </ConfigurationTable>
                    </ConfigurationTables>
                </ServiceImplementation>
                <ServiceImplementation
                 description=""
                 handlerName="Script"
                 name="ValidateComponentMigrateConfigParams">
                    <ConfigurationTables>
                        <ConfigurationTable
                         dataShapeName=""
                         description=""
                         isMultiRow="false"
                         name="Script"
                         ordinal="0">
                            <DataShape>
                                <FieldDefinitions>
                                    <FieldDefinition
                                     baseType="STRING"
                                     description="code"
                                     name="code"
                                     ordinal="0"></FieldDefinition>
                                </FieldDefinitions>
                            </DataShape>
                            <Rows>
                                <Row>
                                    <code>
                                    <![CDATA[
                                    var result = true;
                                    try {
                                    	let componentParams = me.GetComponentMigrateConfigurationParameters();
                                    	for (let key in componentParams) {
                                    		if (!jsonParams[key] && !componentParams[key].optional) {
                                    			result = false;
                                    		}
                                    	}
                                    } catch (err) {
                                    	logger.error(me.name + " - " + err.fileName + ":" + err.lineNumber + " - " + err);
                                    	throw err;
                                    }
                                    ]]>
                                    </code>
                                </Row>
                            </Rows>
                        </ConfigurationTable>
                    </ConfigurationTables>
                </ServiceImplementation>
                <ServiceImplementation
                 description=""
                 handlerName="Script"
                 name="ValidateComponentUpgradeConfigParams">
                    <ConfigurationTables>
                        <ConfigurationTable
                         dataShapeName=""
                         description=""
                         isMultiRow="false"
                         name="Script"
                         ordinal="0">
                            <DataShape>
                                <FieldDefinitions>
                                    <FieldDefinition
                                     baseType="STRING"
                                     description="code"
                                     name="code"
                                     ordinal="0"></FieldDefinition>
                                </FieldDefinitions>
                            </DataShape>
                            <Rows>
                                <Row>
                                    <code>
                                    <![CDATA[
                                    var result = true;
                                    try {
                                    	let componentParams = me.GetComponentUpgradeConfigurationParameters();
                                    	for (let key in componentParams) {
                                    		if (!jsonParams[key] && !componentParams[key].optional) {
                                    			result = false;
                                    		}
                                    	}
                                    } catch (err) {
                                    	logger.error(me.name + " - " + err.fileName + ":" + err.lineNumber + " - " + err);
                                    	throw err;
                                    }
                                    ]]>
                                    </code>
                                </Row>
                            </Rows>
                        </ConfigurationTable>
                    </ConfigurationTables>
                </ServiceImplementation>
            </ServiceImplementations>
            <Subscriptions></Subscriptions>
            <avatar></avatar>
            <DesignTimePermissions>
                <Create></Create>
                <Read></Read>
                <Update></Update>
                <Delete></Delete>
                <Metadata></Metadata>
            </DesignTimePermissions>
            <RunTimePermissions></RunTimePermissions>
            <VisibilityPermissions>
                <Visibility>
                    <Principal
                     isPermitted="true"
                     name="PTC.Base.Default_OR:PTC.Base.Default_UG"
                     type="OrganizationalUnit"></Principal>
                </Visibility>
            </VisibilityPermissions>
            <ConfigurationTableDefinitions>
                <ConfigurationTableDefinition
                 category=""
                 dataShapeName="PTC.Base.ManagerConfiguration"
                 description="Configuration table to store the components core manager"
                 isHidden="false"
                 isMultiRow="true"
                 name="ComponentManager"
                 ordinal="0"
                 source="IMPORT"></ConfigurationTableDefinition>
            </ConfigurationTableDefinitions>
            <ConfigurationTables>
                <ConfigurationTable
                 dataShapeName=""
                 description="Configuration table to store the components core manager"
                 isMultiRow="true"
                 name="ComponentManager"
                 ordinal="0">
                    <DataShape>
                        <FieldDefinitions>
                            <FieldDefinition
                             aspect.isPrimaryKey="true"
                             baseType="STRING"
                             description="unique identifier for the manager that needs to be configured"
                             name="id"
                             ordinal="1"></FieldDefinition>
                            <FieldDefinition
                             aspect.isPrimaryKey="false"
                             aspect.thingShape="PTC.Base.CommonManagement_TS"
                             baseType="THINGNAME"
                             description="Name of the Manager Thing to be configured"
                             name="managerThingName"
                             ordinal="2"></FieldDefinition>
                        </FieldDefinitions>
                    </DataShape>
                    <Rows></Rows>
                </ConfigurationTable>
            </ConfigurationTables>
            <PropertyBindings></PropertyBindings>
            <RemotePropertyBindings></RemotePropertyBindings>
            <RemoteServiceBindings></RemoteServiceBindings>
            <RemoteEventBindings></RemoteEventBindings>
            <AlertConfigurations>
                <AlertDefinitions
                 name="componentDefaultOrg"></AlertDefinitions>
                <AlertDefinitions
                 name="componentDefaultUserGroup"></AlertDefinitions>
                <AlertDefinitions
                 name="componentDeploymentState"></AlertDefinitions>
                <AlertDefinitions
                 name="componentDescription"></AlertDefinitions>
                <AlertDefinitions
                 name="componentMainMashup"></AlertDefinitions>
                <AlertDefinitions
                 name="componentName"></AlertDefinitions>
                <AlertDefinitions
                 name="componentThumbnail"></AlertDefinitions>
                <AlertDefinitions
                 name="componentType"></AlertDefinitions>
                <AlertDefinitions
                 name="componentVersion"></AlertDefinitions>
                <AlertDefinitions
                 name="dependentComponents"></AlertDefinitions>
                <AlertDefinitions
                 name="deployComponentStatus"></AlertDefinitions>
                <AlertDefinitions
                 name="migrateComponentStatus"></AlertDefinitions>
                <AlertDefinitions
                 name="upgradeComponentStatus"></AlertDefinitions>
            </AlertConfigurations>
            <InstanceRunTimePermissions>
                <Permissions
                 resourceName="GetComponentName">
                    <PropertyRead></PropertyRead>
                    <PropertyWrite></PropertyWrite>
                    <ServiceInvoke>
                        <Principal
                         isPermitted="true"
                         name="PTC.Base.Default_UG"
                         type="Group"></Principal>
                    </ServiceInvoke>
                    <EventInvoke></EventInvoke>
                    <EventSubscribe></EventSubscribe>
                </Permissions>
                <Permissions
                 resourceName="GetComponentThumbnail">
                    <PropertyRead></PropertyRead>
                    <PropertyWrite></PropertyWrite>
                    <ServiceInvoke>
                        <Principal
                         isPermitted="true"
                         name="PTC.Base.Default_UG"
                         type="Group"></Principal>
                    </ServiceInvoke>
                    <EventInvoke></EventInvoke>
                    <EventSubscribe></EventSubscribe>
                </Permissions>
                <Permissions
                 resourceName="*">
                    <PropertyRead>
                        <Principal
                         isPermitted="true"
                         name="System"
                         type="User"></Principal>
                    </PropertyRead>
                    <PropertyWrite></PropertyWrite>
                    <ServiceInvoke>
                        <Principal
                         isPermitted="true"
                         name="System"
                         type="User"></Principal>
                    </ServiceInvoke>
                    <EventInvoke></EventInvoke>
                    <EventSubscribe></EventSubscribe>
                </Permissions>
                <Permissions
                 resourceName="GetComponentDescription">
                    <PropertyRead></PropertyRead>
                    <PropertyWrite></PropertyWrite>
                    <ServiceInvoke>
                        <Principal
                         isPermitted="true"
                         name="PTC.Base.Default_UG"
                         type="Group"></Principal>
                    </ServiceInvoke>
                    <EventInvoke></EventInvoke>
                    <EventSubscribe></EventSubscribe>
                </Permissions>
                <Permissions
                 resourceName="GetComponentType">
                    <PropertyRead></PropertyRead>
                    <PropertyWrite></PropertyWrite>
                    <ServiceInvoke>
                        <Principal
                         isPermitted="true"
                         name="PTC.Base.Default_UG"
                         type="Group"></Principal>
                    </ServiceInvoke>
                    <EventInvoke></EventInvoke>
                    <EventSubscribe></EventSubscribe>
                </Permissions>
                <Permissions
                 resourceName="GetComponentVersion">
                    <PropertyRead></PropertyRead>
                    <PropertyWrite></PropertyWrite>
                    <ServiceInvoke>
                        <Principal
                         isPermitted="true"
                         name="PTC.Base.Default_UG"
                         type="Group"></Principal>
                    </ServiceInvoke>
                    <EventInvoke></EventInvoke>
                    <EventSubscribe></EventSubscribe>
                </Permissions>
            </InstanceRunTimePermissions>
        </ThingShape>
    </ThingShapes>
</Entities>
